ecgi/__init__.py
ecgi/processing.py
ecgi/utils.py
ecgi-0.0.0.dist-info/LICENSE
ecgi-0.0.0.dist-info/METADATA
ecgi-0.0.0.dist-info/WHEEL
ecgi-0.0.0.dist-info/top_level.txt
ecgi-0.0.0.dist-info/RECORD
